bini.py
bini-1.0.1.dist-info/DESCRIPTION.rst
bini-1.0.1.dist-info/METADATA
bini-1.0.1.dist-info/RECORD
bini-1.0.1.dist-info/WHEEL
bini-1.0.1.dist-info/metadata.json
bini-1.0.1.dist-info/top_level.txt
