Metadata-Version: 2.0
Name: bini
Version: 1.0.1
Summary: A library for binary ini-file(bini) manipulation in Python3
Home-page: UNKNOWN
Author: Tobias Weise
Author-email: tobias_weise@gmx.de
License: BSD3
Keywords: bini ini configuration freelancer windows
Platform: UNKNOWN
Classifier: Development Status :: 4 - Beta
Classifier: Intended Audience :: Developers
Classifier: License :: OSI Approved :: BSD License
Classifier: Programming Language :: Python :: 3
